CHANGELOG.txt
MANIFEST.in
README.md
pyproject.toml
setup.cfg
setup.py
tox.ini
src/insecure_but_secure_enough/__init__.py
src/insecure_but_secure_enough/py.typed
src/insecure_but_secure_enough.egg-info/PKG-INFO
src/insecure_but_secure_enough.egg-info/SOURCES.txt
src/insecure_but_secure_enough.egg-info/dependency_links.txt
src/insecure_but_secure_enough.egg-info/not-zip-safe
src/insecure_but_secure_enough.egg-info/requires.txt
src/insecure_but_secure_enough.egg-info/top_level.txt
tests/__init__.py
tests/_utils.py
tests/test_core.py
tests/test_unit_obfuscator.py