Metadata-Version: 2.4
Name: insecure_but_secure_enough
Version: 0.3.0
Summary: Lightweight tools for signing and encrypting cookies, urls and stuff. This package isn't really secure, but it is secure enough for most needs.
Home-page: https://github.com/jvanasco/insecure_but_secure_enough
Author: Jonathan Vanasco
Author-email: jonathan@findmeon.com
License: MIT
Keywords: web pylons pyramid
Classifier: Intended Audience :: Developers
Classifier: Programming Language :: Python :: 3
Classifier: Programming Language :: Python :: 3.7
Classifier: Programming Language :: Python :: 3.8
Classifier: Programming Language :: Python :: 3.9
Classifier: Programming Language :: Python :: 3.10
Classifier: Programming Language :: Python :: 3.11
Classifier: Programming Language :: Python :: 3.12
Classifier: Programming Language :: Python :: 3.13
Requires-Dist: pycryptodomex
Requires-Dist: simplejson
Requires-Dist: typing_extensions
Provides-Extra: testing
Requires-Dist: pytest; extra == "testing"
Dynamic: author
Dynamic: author-email
Dynamic: classifier
Dynamic: description
Dynamic: description-content-type
Dynamic: home-page
Dynamic: keywords
Dynamic: license
Dynamic: provides-extra
Dynamic: requires-dist
Dynamic: summary
